podcast_summarizer/__init__.py
podcast_summarizer/cli.py
podcast_summarizer/summarizer.py
podcast_summarizer/youtube.py
podcast_summarizer-0.3.1.dist-info/LICENSE
podcast_summarizer-0.3.1.dist-info/METADATA
podcast_summarizer-0.3.1.dist-info/WHEEL
podcast_summarizer-0.3.1.dist-info/entry_points.txt
podcast_summarizer-0.3.1.dist-info/RECORD
