Metadata-Version: 2.1
Name: podcast-summarizer
Version: 0.3.1
Summary: Summarizes podcasts.
License: MIT
Author: Diego Quinteiro
Author-email: diegoquinteiro@gmail.com
Requires-Python: >=3.9,<4.0
Classifier: License :: OSI Approved :: MIT License
Classifier: Programming Language :: Python :: 3
Classifier: Programming Language :: Python :: 3.9
Classifier: Programming Language :: Python :: 3.10
Classifier: Programming Language :: Python :: 3.11
Requires-Dist: click (>=8.1.4,<9.0.0)
Requires-Dist: click-spinner (>=0.1.10,<0.2.0)
Requires-Dist: openai (>=0.27.8,<0.28.0)
Requires-Dist: openai-whisper (==20230314)
Requires-Dist: tiktoken (==0.3.3)
Requires-Dist: webvtt-py (>=0.4.6,<0.5.0)
Requires-Dist: yt-dlp (>=2023.7.6,<2024.0.0)
